{"status":200,"result":{"postcode":"E5 8HT","quality":1,"eastings":535071,"northings":185458,"country":"England","nhs_ha":"London","longitude":-0.0532444526771821,"latitude":51.5518497175874,"parliamentary_constituency":"Hackney South and Shoreditch","european_electoral_region":"London","primary_care_trust":"City and Hackney Teaching","region":"London","lsoa":"Hackney 017B","msoa":"Hackney 017","incode":"8HT","outcode":"E5","admin_district":"Hackney","parish":"Hackney, unparished area","admin_county":null,"admin_ward":"Homerton","ccg":"NHS City and Hackney","nuts":"Hackney and Newham","codes":{"admin_district":"E09000012","admin_county":"E99999999","admin_ward":"E05009376","parish":"E43000202","ccg":"E38000035","nuts":"UKI41"}}}